adafruit_bus_device/__init__.py
adafruit_bus_device/i2c_device.py
adafruit_bus_device/spi_device.py
adafruit_circuitpython_busdevice-5.2.6.dist-info/LICENSE
adafruit_circuitpython_busdevice-5.2.6.dist-info/METADATA
adafruit_circuitpython_busdevice-5.2.6.dist-info/WHEEL
adafruit_circuitpython_busdevice-5.2.6.dist-info/top_level.txt
adafruit_circuitpython_busdevice-5.2.6.dist-info/RECORD
