Metadata-Version: 2.1
Name: adafruit-circuitpython-busdevice
Version: 5.2.6
Summary: CircuitPython bus device classes to manage bus sharing.
Author-email: Adafruit Industries <circuitpython@adafruit.com>
License: MIT
Project-URL: Homepage, https://github.com/adafruit/Adafruit_CircuitPython_BusDevice
Keywords: adafruit,spi,i2c,bus,device,micropython,circuitpython
Classifier: Intended Audience :: Developers
Classifier: Topic :: Software Development :: Libraries
Classifier: Topic :: Software Development :: Embedded Systems
Classifier: Topic :: System :: Hardware
Classifier: License :: OSI Approved :: MIT License
Classifier: Programming Language :: Python :: 3
Provides-Extra: optional
License-File: LICENSE
